{
  "project_info": {
    "project_number": "536701149573",
    "project_id": "hotel-f84db",
    "storage_bucket": "hotel-f84db.firebasestorage.app"
  },
  "client": [
    {
      "client_info": {
        "mobilesdk_app_id": "1:536701149573:android:6e3f7c230003d4321924ec",
        "android_client_info": {
          "package_name": "com.hotel.dz"
        }
      },
      "oauth_client": [],
      "api_key": [
        {
          "current_key": "AIzaSyBygH4-4mmUJe-6UL7iExAPxNwiVv3WIlA"
        }
      ],
      "services": {
        "appinvite_service": {
          "other_platform_oauth_client": []
        }
      }
    }
  ],
  "configuration_version": "1"
}